{"code":1,"msg":"数据列表","page":1,"pagecount":25,"limit":"50","total":1236,"list":[{"vod_id":1236,"vod_name":"071322-001-carib-1080p","type_id":5,"type_name":"短视频","vod_en":"","vod_time":"1970-01-01 08:00:00","vod_remarks":"","vod_play_from":"lmm3u8"},{"vod_id":1235,"vod_name":"最終幻想 Tifa Lockhart 體驗終極口腔快感 - BulgingSenpai","type_id":5,"type_name":"短视频","vod_en":"","vod_time":"1970-01-01 08:00:00","vod_remarks":"","vod_play_from":"lmm3u8"},{"vod_id":1234,"vod_name":"震惊！你没见过的69深喉","type_id":5,"type_name":"短视频","vod_en":"","vod_time":"1970-01-01 08:00:00","vod_remarks":"","vod_play_from":"lmm3u8"},{"vod_id":1233,"vod_name":"在公共试衣间吹箫。 吸公鸡和吞下去暨。 里奥·克莱奥","type_id":5,"type_name":"短视频","vod_en":"","vod_time":"1970-01-01 08:00:00","vod_remarks":"","vod_play_from":"lmm3u8"},{"vod_id":1232,"vod_name":"在火车上的公共鸡巴闪光最终以一个陌生人的打手枪和口交结束。","type_id":5,"type_name":"短视频","vod_en":"","vod_time":"1970-01-01 08:00:00","vod_remarks":"","vod_play_from":"lmm3u8"},{"vod_id":1231,"vod_name":"用口交和射在她嘴上的坏老师醒来","type_id":5,"type_name":"短视频","vod_en":"","vod_time":"1970-01-01 08:00:00","vod_remarks":"","vod_play_from":"lmm3u8"},{"vod_id":1230,"vod_name":"一个不知名的女孩让我在公共汽车上打手枪。 公开的当众","type_id":5,"type_name":"短视频","vod_en":"","vod_time":"1970-01-01 08:00:00","vod_remarks":"","vod_play_from":"lmm3u8"},{"vod_id":1229,"vod_name":"无知女孩野外偶遇我打飞机并帮我口出","type_id":5,"type_name":"短视频","vod_en":"","vod_time":"1970-01-01 08:00:00","vod_remarks":"","vod_play_from":"lmm3u8"},{"vod_id":1228,"vod_name":"小姐姐主动地深喉爆射","type_id":5,"type_name":"短视频","vod_en":"","vod_time":"1970-01-01 08:00:00","vod_remarks":"","vod_play_from":"lmm3u8"},{"vod_id":1227,"vod_name":"我喜欢射在她的小嘴里","type_id":5,"type_name":"短视频","vod_en":"","vod_time":"1970-01-01 08:00:00","vod_remarks":"","vod_play_from":"lmm3u8"},{"vod_id":1226,"vod_name":"我暨在我的荡妇同学的嘴里","type_id":5,"type_name":"短视频","vod_en":"","vod_time":"1970-01-01 08:00:00","vod_remarks":"","vod_play_from":"lmm3u8"},{"vod_id":1225,"vod_name":"吞进去，把老子的鸡巴吞进去","type_id":5,"type_name":"短视频","vod_en":"","vod_time":"1970-01-01 08:00:00","vod_remarks":"","vod_play_from":"lmm3u8"},{"vod_id":1224,"vod_name":"她的喉咙里有很多暨，口服体内射精","type_id":5,"type_name":"短视频","vod_en":"","vod_time":"1970-01-01 08:00:00","vod_remarks":"","vod_play_from":"lmm3u8"},{"vod_id":1223,"vod_name":"停车场吹喇叭，他竟射我嘴里！","type_id":5,"type_name":"短视频","vod_en":"","vod_time":"1970-01-01 08:00:00","vod_remarks":"","vod_play_from":"lmm3u8"},{"vod_id":1222,"vod_name":"素人被抽动的鸡巴射满嘴","type_id":5,"type_name":"短视频","vod_en":"","vod_time":"1970-01-01 08:00:00","vod_remarks":"","vod_play_from":"lmm3u8"},{"vod_id":1221,"vod_name":"饥渴难耐在机场口交","type_id":5,"type_name":"短视频","vod_en":"","vod_time":"1970-01-01 08:00:00","vod_remarks":"","vod_play_from":"lmm3u8"},{"vod_id":1220,"vod_name":"惊人的特写吹箫与搏动暨在嘴","type_id":5,"type_name":"短视频","vod_en":"","vod_time":"1970-01-01 08:00:00","vod_remarks":"","vod_play_from":"lmm3u8"},{"vod_id":1219,"vod_name":"公交车上陌生人口交，我付钱给她","type_id":5,"type_name":"短视频","vod_en":"","vod_time":"1970-01-01 08:00:00","vod_remarks":"","vod_play_from":"lmm3u8"},{"vod_id":1218,"vod_name":"公交车上美眉帮我打飞机并口交吞精","type_id":5,"type_name":"短视频","vod_en":"","vod_time":"1970-01-01 08:00:00","vod_remarks":"","vod_play_from":"lmm3u8"},{"vod_id":1217,"vod_name":"公交车上啃鸡鸡 情到深处射嘴里","type_id":5,"type_name":"短视频","vod_en":"","vod_time":"1970-01-01 08:00:00","vod_remarks":"","vod_play_from":"lmm3u8"},{"vod_id":1216,"vod_name":"给红发美女口交并在他嘴里大爆射","type_id":5,"type_name":"短视频","vod_en":"","vod_time":"1970-01-01 08:00:00","vod_remarks":"","vod_play_from":"lmm3u8"},{"vod_id":1215,"vod_name":"公交车上的调皮妻子","type_id":5,"type_name":"短视频","vod_en":"","vod_time":"1970-01-01 08:00:00","vod_remarks":"","vod_play_from":"lmm3u8"},{"vod_id":1214,"vod_name":"反vaxxxer女朋友得到了“cumvac”的一部分","type_id":5,"type_name":"短视频","vod_en":"","vod_time":"1970-01-01 08:00:00","vod_remarks":"","vod_play_from":"lmm3u8"},{"vod_id":1213,"vod_name":"赌注荡妇烂鸡巴直到暨在嘴里","type_id":5,"type_name":"短视频","vod_en":"","vod_time":"1970-01-01 08:00:00","vod_remarks":"","vod_play_from":"lmm3u8"},{"vod_id":1212,"vod_name":"车后座的金发骑手","type_id":5,"type_name":"短视频","vod_en":"","vod_time":"1970-01-01 08:00:00","vod_remarks":"","vod_play_from":"lmm3u8"},{"vod_id":1211,"vod_name":"蒂法口交（有声）","type_id":5,"type_name":"短视频","vod_en":"","vod_time":"1970-01-01 08:00:00","vod_remarks":"","vod_play_from":"lmm3u8"},{"vod_id":1210,"vod_name":"爱情#很口吃，很深，舌头很长-口交","type_id":5,"type_name":"短视频","vod_en":"","vod_time":"1970-01-01 08:00:00","vod_remarks":"","vod_play_from":"lmm3u8"},{"vod_id":1209,"vod_name":"Публичный минет в поезед!","type_id":5,"type_name":"短视频","vod_en":"","vod_time":"1970-01-01 08:00:00","vod_remarks":"","vod_play_from":"lmm3u8"},{"vod_id":1208,"vod_name":"Оральный Секс С 18 Летней Девочкой, Мощно Кончил В Рот Кончил В Горло, Я Знаю Как Сосать - SadAndWet","type_id":5,"type_name":"短视频","vod_en":"","vod_time":"1970-01-01 08:00:00","vod_remarks":"","vod_play_from":"lmm3u8"},{"vod_id":1207,"vod_name":"Young Couple having Fun in Public Bus","type_id":5,"type_name":"短视频","vod_en":"","vod_time":"1970-01-01 08:00:00","vod_remarks":"","vod_play_from":"lmm3u8"},{"vod_id":1206,"vod_name":"UNDERSTAND TRAIN + REAL = RUN IN THE MOUTH","type_id":5,"type_name":"短视频","vod_en":"","vod_time":"1970-01-01 08:00:00","vod_remarks":"","vod_play_from":"lmm3u8"},{"vod_id":1205,"vod_name":"Valentine Chronicles - 3D Monster Animation","type_id":5,"type_name":"短视频","vod_en":"","vod_time":"1970-01-01 08:00:00","vod_remarks":"","vod_play_from":"lmm3u8"},{"vod_id":1204,"vod_name":"Tifa Loves Dick between Tits (sex Tifa - Tifa Porn - Final Fantasy Porn - Tifa Lockhart Porn)","type_id":5,"type_name":"短视频","vod_en":"","vod_time":"1970-01-01 08:00:00","vod_remarks":"","vod_play_from":"lmm3u8"},{"vod_id":1203,"vod_name":"Uber Driver Gets a Hot Blowjob after Picking a Hot MILF after a Party","type_id":5,"type_name":"短视频","vod_en":"","vod_time":"1970-01-01 08:00:00","vod_remarks":"","vod_play_from":"lmm3u8"},{"vod_id":1202,"vod_name":"Tifa Lockhart - Anal Creampie","type_id":5,"type_name":"短视频","vod_en":"","vod_time":"1970-01-01 08:00:00","vod_remarks":"","vod_play_from":"lmm3u8"},{"vod_id":1201,"vod_name":"Teacher Jerks off a Student&#039s Dick in University Class until he Cums - MissCreamy","type_id":5,"type_name":"短视频","vod_en":"","vod_time":"1970-01-01 08:00:00","vod_remarks":"","vod_play_from":"lmm3u8"},{"vod_id":1200,"vod_name":"Stranger Jerked and Suck me in the Train","type_id":5,"type_name":"短视频","vod_en":"","vod_time":"1970-01-01 08:00:00","vod_remarks":"","vod_play_from":"lmm3u8"},{"vod_id":1199,"vod_name":"SUPER RISKY Sloppy Blowjob on Chicago Ferris Wheel! he came so Fast...","type_id":5,"type_name":"短视频","vod_en":"","vod_time":"1970-01-01 08:00:00","vod_remarks":"","vod_play_from":"lmm3u8"},{"vod_id":1198,"vod_name":"Serah Farron Face Blowjob 3d","type_id":5,"type_name":"短视频","vod_en":"","vod_time":"1970-01-01 08:00:00","vod_remarks":"","vod_play_from":"lmm3u8"},{"vod_id":1197,"vod_name":"Road Head on a Road Trip! Sloppy Blowjob in the Truck!","type_id":5,"type_name":"短视频","vod_en":"","vod_time":"1970-01-01 08:00:00","vod_remarks":"","vod_play_from":"lmm3u8"},{"vod_id":1196,"vod_name":"Road Head and Facial","type_id":5,"type_name":"短视频","vod_en":"","vod_time":"1970-01-01 08:00:00","vod_remarks":"","vod_play_from":"lmm3u8"},{"vod_id":1195,"vod_name":"Risky Public Blowjob in the Double-decker City Bus","type_id":5,"type_name":"短视频","vod_en":"","vod_time":"1970-01-01 08:00:00","vod_remarks":"","vod_play_from":"lmm3u8"},{"vod_id":1194,"vod_name":"Risky Blowjob. the Girl Began to Pester the Guy in the Fitting Room.","type_id":5,"type_name":"短视频","vod_en":"","vod_time":"1970-01-01 08:00:00","vod_remarks":"","vod_play_from":"lmm3u8"},{"vod_id":1193,"vod_name":"Risky Blowjob in a Plane to Berlin - Mile High Club - Amateur MySweetApple","type_id":5,"type_name":"短视频","vod_en":"","vod_time":"1970-01-01 08:00:00","vod_remarks":"","vod_play_from":"lmm3u8"},{"vod_id":1192,"vod_name":"Real Public Road Trip Road Head- Licking, Gagging, Swallow- Joey Lee","type_id":5,"type_name":"短视频","vod_en":"","vod_time":"1970-01-01 08:00:00","vod_remarks":"","vod_play_from":"lmm3u8"},{"vod_id":1191,"vod_name":"Resident Evil 3 Jill Sloppy Blowjob","type_id":5,"type_name":"短视频","vod_en":"","vod_time":"1970-01-01 08:00:00","vod_remarks":"","vod_play_from":"lmm3u8"},{"vod_id":1190,"vod_name":"Real Public Quickie Handjob in Mini Bus, she like It!","type_id":5,"type_name":"短视频","vod_en":"","vod_time":"1970-01-01 08:00:00","vod_remarks":"","vod_play_from":"lmm3u8"},{"vod_id":1189,"vod_name":"Real- Caught BJ in Uber &amp Kicked Out!","type_id":5,"type_name":"短视频","vod_en":"","vod_time":"1970-01-01 08:00:00","vod_remarks":"","vod_play_from":"lmm3u8"},{"vod_id":1188,"vod_name":"Real Amateur Public Blow Job in Ski Lift #2","type_id":5,"type_name":"短视频","vod_en":"","vod_time":"1970-01-01 08:00:00","vod_remarks":"","vod_play_from":"lmm3u8"},{"vod_id":1187,"vod_name":"Quick Blow Job &amp Swallow on the Train","type_id":5,"type_name":"短视频","vod_en":"","vod_time":"1970-01-01 08:00:00","vod_remarks":"","vod_play_from":"lmm3u8"}],"class":[{"type_id":1,"type_pid":0,"type_name":"国产无码"},{"type_id":2,"type_pid":0,"type_name":"日韩无码"},{"type_id":3,"type_pid":0,"type_name":"日韩有码"},{"type_id":4,"type_pid":0,"type_name":"欧美无码"},{"type_id":5,"type_pid":0,"type_name":"短视频"}]}